{"assets/fonts/agustina.otf":["assets/fonts/agustina.otf"],"assets/fonts/montserrat.ttf":["assets/fonts/montserrat.ttf"],"assets/image/Logo.jpg":["assets/image/Logo.jpg"],"assets/image/WhatsApp Image 2023-03-12 at 3.45.23 PM.jpeg":["assets/image/WhatsApp Image 2023-03-12 at 3.45.23 PM.jpeg"],"assets/image/alan.png":["assets/image/alan.png"],"assets/image/dev.png":["assets/image/dev.png"],"assets/image/hi.gif":["assets/image/hi.gif"],"assets/image/ia.png":["assets/image/ia.png"],"assets/image/inout.png":["assets/image/inout.png"],"assets/image/lafia.png":["assets/image/lafia.png"],"assets/image/th.png":["assets/image/th.png"],"assets/image/ware.jpeg":["assets/image/ware.jpeg"],"assets/image/ware.png":["assets/image/ware.png"],"assets/image/xam.png":["assets/image/xam.png"],"packages/cupertino_icons/assets/CupertinoIcons.ttf":["packages/cupertino_icons/assets/CupertinoIcons.ttf"]}